pxr/.libs/libPxrSdf.dylib
pxr/Sdf/__init__.py
pxr/Sdf/_sdf.so
pxr/pluginfo/sdf/resources/plugInfo.json
pxr_sdf-25.8.dist-info/METADATA
pxr_sdf-25.8.dist-info/WHEEL
pxr_sdf-25.8.dist-info/licenses/NOTICE.txt
pxr_sdf-25.8.dist-info/licenses/LICENSE.txt
pxr_sdf-25.8.dist-info/RECORD
